[
    {
        "artist": "Tiakola",
        "track": "Si j'savais"
    },
    {
        "artist": "Burna Boy",
        "track": "It's Plenty"
    },
    {
        "artist": "Shakira",
        "track": "Hips Don't Lie (feat. Wyclef Jean)"
    },
    {
        "artist": "SCH",
        "track": "Mode Akimbo (feat. Jul)"
    },
    {
        "artist": "Keen'V",
        "track": "A L'horizontal"
    },
    {
        "artist": "Shakira Ft. Wyclef Jean",
        "track": "Hips Don't Lie (Radio Edit)"
    },
    {
        "artist": "Black Eyed Peas",
        "track": "Pump It"
    },
    {
        "artist": "PLK",
        "track": "Un peu de haine"
    },
    {
        "artist": "Icona Pop Ft. Charli XCX",
        "track": "I Love It (Extended Mix By Fuvi Clan)"
    },
    {
        "artist": "Macklemore",
        "track": "Thrift Shop (feat. Wanz)"
    }
]