[
    {
        "artist": "Davy One",
        "track": "Jeu De Jambes (Extended Mix By Fuvi Clan)"
    },
    {
        "artist": "JEY BROWNIE",
        "track": "GTB"
    },
    {
        "artist": "Kavinsky",
        "track": "Nightcall"
    },
    {
        "artist": "Jul",
        "track": "Inspi d'ailleurs"
    },
    {
        "artist": "Tiakola x Dave",
        "track": "Meridian (Extended Mix By Fuvi Clan)"
    },
    {
        "artist": "Zed, Josman, Jolagreen23",
        "track": "Malcom X (Extended Mix By Fuvi Clan)"
    },
    {
        "artist": "PZK",
        "track": "Les filles adorent"
    },
    {
        "artist": "Tragédie",
        "track": "Hey Oh (Radio Edit)"
    },
    {
        "artist": "Bolémvn",
        "track": "Ça canarde"
    },
    {
        "artist": "Giant",
        "track": "AH TXE TXE"
    }
]