[
    {
        "artist": "Soprano",
        "track": "En Feu (Extended Mix)"
    },
    {
        "artist": "Aya Nakamura",
        "track": "Chimiyé (Extended Mix By Fuvi Clan)"
    },
    {
        "artist": "KeBlack",
        "track": "Complètement Sonné (Extended Mix By Fuvi Clan)"
    },
    {
        "artist": "Jul, Sch, Naps, Kofs, Elams, Solda, Houari, Soso Maness",
        "track": "Bande Organisée (Ravage Intro)"
    },
    {
        "artist": "Lady Gaga",
        "track": "Born This Way"
    },
    {
        "artist": "Naza, SDM",
        "track": "Tout Donner (Extended Mix By Fuvi Clan)"
    },
    {
        "artist": "Kay Flock ft Cardi B, Dougie B & Bory300",
        "track": "Shake It (HH Dirty Intro)"
    },
    {
        "artist": "Aya Nakamura",
        "track": "Jolie nana"
    },
    {
        "artist": "Werenoi",
        "track": "Scarface (Extended Mix By Fuvi Clan)"
    },
    {
        "artist": "Heuss L'enfoiré",
        "track": "Moulaga"
    }
]