[
    {
        "artist": "Magic System",
        "track": "Ambiance à l'africaine"
    },
    {
        "artist": "Kamelon Officiel, Mikado",
        "track": "La Belette (Extended Mix By Fuvi Clan)"
    },
    {
        "artist": "Taio Cruz",
        "track": "Dynamite (DÈNCE Remix)"
    },
    {
        "artist": "Soolking Ft. Niska",
        "track": "Balader (Extended Mix By Fuvi Clan)"
    },
    {
        "artist": "Dadju & Tayc",
        "track": "La Vie D'un ... Ma Préférée (Extended Mix By Fuvi Clan)"
    },
    {
        "artist": "Rohff",
        "track": "Qui est l'exemple ? (Original Mix)"
    },
    {
        "artist": "Mark Ronson",
        "track": "Uptown Funk (feat. Bruno Mars)"
    },
    {
        "artist": "Fatal Bazooka",
        "track": "Ce matin va être une pure soirée (feat. Big Ali, PZK, Dogg SoSo, Chris Prolls)"
    },
    {
        "artist": "Flo Rida",
        "track": "Club Can't Handle Me (feat. David Guetta)"
    },
    {
        "artist": "Vacra",
        "track": "Tiki Taka"
    }
]