[
    {
        "artist": "MC Fioti",
        "track": "Bum Bum Tam Tam"
    },
    {
        "artist": "NAPS Ft. GIMS",
        "track": "Best Life (Dj R'an Edit)"
    },
    {
        "artist": "Daddy Yankee",
        "track": "Dura"
    },
    {
        "artist": "Dadju",
        "track": "Oublie-le"
    },
    {
        "artist": "Mustard & Migos",
        "track": "Pure Water (HH Dirty Intro)"
    },
    {
        "artist": "Niska Ft. Madrane",
        "track": "Bandit Chef (Extended Mix By Fuvi Clan)"
    },
    {
        "artist": "Theodora",
        "track": "Kongolese Sous BBL (Extended Mix By Fuvi Clan)"
    },
    {
        "artist": "Yolanda Be Cool & DCUP",
        "track": "We No Speak Americano (Castion Remix)"
    },
    {
        "artist": "Eminem x Bad Bunny",
        "track": "Real Slim Shady x Titi Me Pregunto (Elias Posh Mashup)"
    },
    {
        "artist": "Bad Bunny",
        "track": "DÁKITI"
    }
]