[
    {
        "artist": "Jennifer Lopez",
        "track": "On The Floor"
    },
    {
        "artist": "Master KG",
        "track": "Jerusalema (feat. Nomcebo Zikode)"
    },
    {
        "artist": "Jul",
        "track": "Tu la love"
    },
    {
        "artist": "DJ Sad",
        "track": "Il est marié"
    },
    {
        "artist": "Ariana Grande",
        "track": "Thank You, Next (Intro Clean)"
    },
    {
        "artist": "Ninho FT. Niska",
        "track": "Elle A Mal (Extended Mix By Fuvi Clan)"
    },
    {
        "artist": "Guru Josh Project",
        "track": "Infinity 2008"
    },
    {
        "artist": "Eminem",
        "track": "Houdini (Dunisco Remix)"
    },
    {
        "artist": "J Balvin x Willy William x Skrillex",
        "track": "Mi Gente In Da Getto (Segue Edit 105-127 BPM Transition)"
    },
    {
        "artist": "Vacra",
        "track": "Tiki Taka (Extended Mix By Fuvi Clan)"
    }
]